{
  "version": "6.3.0",
  "flags": {},
  "shapes": [
    {
      "label": "CHILDREN",
      "points": [
        [
          645.0420168067226,
          17.983193277310907
        ],
        [
          859.3277310924369,
          329.74789915966386
        ]
      ],
      "group_id": null,
      "description": "",
      "shape_type": "rectangle",
      "flags": {},
      "mask": null
    },
    {
      "label": "CHILDREN",
      "points": [
        [
          867.7310924369747,
          8.73949579831931
        ],
        [
          1170.2521008403362,
          278.4873949579832
        ]
      ],
      "group_id": null,
      "description": "",
      "shape_type": "rectangle",
      "flags": {},
      "mask": null
    }
  ],
  "imagePath": "118_frames492.jpg",
  "imageData": null,
  "imageHeight": 720,
  "imageWidth": 1280
}