{
  "version": "6.3.0",
  "flags": {},
  "shapes": [
    {
      "label": "Children",
      "points": [
        [
          632.016806722689,
          699.4957983193277
        ],
        [
          721.9327731092437,
          607.0588235294118
        ],
        [
          484.9579831932773,
          323.8655462184874
        ],
        [
          546.3025210084033,
          249.07563025210084
        ],
        [
          694.2016806722689,
          428.06722689075633
        ],
        [
          790.0,
          275.12605042016804
        ],
        [
          742.1008403361344,
          41.51260504201679
        ],
        [
          850.5042016806723,
          4.5378151260504005
        ],
        [
          967.3109243697479,
          11.260504201680654
        ],
        [
          988.3193277310925,
          229.74789915966386
        ],
        [
          1151.3445378151262,
          591.09243697479
        ],
        [
          1122.7731092436975,
          701.1764705882354
        ]
      ],
      "group_id": null,
      "description": "",
      "shape_type": "polygon",
      "flags": {},
      "mask": null
    }
  ],
  "imagePath": "118_frames58.jpg",
  "imageData": null,
  "imageHeight": 720,
  "imageWidth": 1280
}