{
  "version": "6.3.0",
  "flags": {},
  "shapes": [
    {
      "label": "person",
      "points": [
        [
          606.3865546218486,
          379.327731092437
        ],
        [
          876.1344537815125,
          649.9159663865546
        ]
      ],
      "group_id": null,
      "description": "",
      "shape_type": "rectangle",
      "flags": {},
      "mask": null
    },
    {
      "label": "BOX",
      "points": [
        [
          978.6554621848738,
          299.4957983193277
        ],
        [
          1266.8907563025211,
          533.109243697479
        ]
      ],
      "group_id": null,
      "description": "",
      "shape_type": "rectangle",
      "flags": {},
      "mask": null
    }
  ],
  "imagePath": "frames49.jpg",
  "imageData": null,
  "imageHeight": 720,
  "imageWidth": 1280
}