{
  "version": "6.3.0",
  "flags": {},
  "shapes": [
    {
      "label": "person",
      "points": [
        [
          411.42857142857133,
          714.6218487394958
        ],
        [
          613.9495798319327,
          657.4789915966387
        ],
        [
          633.2773109243697,
          599.4957983193277
        ],
        [
          582.8571428571428,
          559.1596638655462
        ],
        [
          578.6554621848738,
          503.69747899159665
        ],
        [
          594.6218487394957,
          396.1344537815126
        ],
        [
          784.5378151260503,
          345.7142857142857
        ],
        [
          866.8907563025209,
          422.18487394957987
        ],
        [
          867.7310924369747,
          555.7983193277311
        ],
        [
          832.4369747899159,
          654.1176470588235
        ],
        [
          875.2941176470588,
          712.9411764705883
        ]
      ],
      "group_id": null,
      "description": "",
      "shape_type": "polygon",
      "flags": {},
      "mask": null
    },
    {
      "label": "No object",
      "points": [
        [
          982.016806722689,
          408.73949579831935
        ],
        [
          951.7647058823529,
          348.2352941176471
        ],
        [
          1257.6470588235295,
          305.3781512605042
        ],
        [
          1280.0,
          391.99579831932766
        ],
        [
          1279.4957983193278,
          613.781512605042
        ],
        [
          1063.5294117647059,
          564.2016806722689
        ]
      ],
      "group_id": null,
      "description": "",
      "shape_type": "polygon",
      "flags": {},
      "mask": null
    }
  ],
  "imagePath": "frames1.jpg",
  "imageData": null,
  "imageHeight": 720,
  "imageWidth": 1280
}