{
  "version": "6.3.0",
  "flags": {},
  "shapes": [
    {
      "label": "person",
      "points": [
        [
          615.6302521008403,
          378.4873949579832
        ],
        [
          870.2521008403361,
          669.2436974789916
        ]
      ],
      "group_id": null,
      "description": "",
      "shape_type": "rectangle",
      "flags": {},
      "mask": null
    },
    {
      "label": "BOX",
      "points": [
        [
          965.2100840336134,
          332.2689075630252
        ],
        [
          1264.3697478991596,
          540.6722689075631
        ]
      ],
      "group_id": null,
      "description": "",
      "shape_type": "rectangle",
      "flags": {},
      "mask": null
    }
  ],
  "imagePath": "frames33.jpg",
  "imageData": null,
  "imageHeight": 720,
  "imageWidth": 1280
}